smtp_send/__init__.py
smtp_send/__main__.py
smtp_send/cli.py
smtp_send/letter.py
smtp_send/mail_service.py
smtp_send/tools.py
smtp_send-0.0.7.dist-info/LICENSE
smtp_send-0.0.7.dist-info/METADATA
smtp_send-0.0.7.dist-info/WHEEL
smtp_send-0.0.7.dist-info/entry_points.txt
smtp_send-0.0.7.dist-info/top_level.txt
smtp_send-0.0.7.dist-info/RECORD
