Metadata-Version: 2.1
Name: smtp-send
Version: 0.0.7
Summary: 命令行邮件发送工具
Home-page: https://github.com/canovie/smtp-send
Author: Jerry Chan
Author-email: jerry@mydream.ink
License: MIT
Keywords: smtp-send,send-email,pysendemail,sendemail,email
Platform: UNKNOWN
Classifier: Development Status :: 5 - Production/Stable
Classifier: Intended Audience :: Developers
Classifier: Topic :: Software Development :: Libraries :: Python Modules
Classifier: License :: OSI Approved :: MIT License
Classifier: Programming Language :: Python :: 3
Classifier: Programming Language :: Python :: 3 :: Only
Requires-Dist: python-dotenv (>=0.10.3)
Requires-Dist: jinja2 (>=2.10.3)
